pydantic_bq/__init__.py
pydantic_bq/client.py
pydantic_bq/schema.py
pydantic_bq/settings.py
pydantic_bq/types.py
pydantic_bq-0.1.5.dist-info/METADATA
pydantic_bq-0.1.5.dist-info/WHEEL
pydantic_bq-0.1.5.dist-info/RECORD
