Metadata-Version: 2.4
Name: pydantic-bq
Version: 0.1.5
Summary: Pydantic-based BigQuery client for type-safe schema definition and data operations
Author: TutorCruncher
License: MIT
Keywords: bigquery,data,google-cloud,pydantic
Classifier: Development Status :: 4 - Beta
Classifier: Intended Audience :: Developers
Classifier: License :: OSI Approved :: MIT License
Classifier: Programming Language :: Python :: 3
Classifier: Programming Language :: Python :: 3.12
Classifier: Topic :: Database
Requires-Python: >=3.12
Requires-Dist: google-auth>=2.43
Requires-Dist: google-cloud-bigquery>=3.38
Requires-Dist: pandas>=2.3
Requires-Dist: pydantic-settings>=2.12
Requires-Dist: pydantic>=2.12
